kindwise/__init__.py
kindwise/core.py
kindwise/insect.py
kindwise/models.py
kindwise/mushroom.py
kindwise/plant.py
kindwise/resources/views.insect.json
kindwise/resources/views.mushroom.json
kindwise/resources/views.plant.disease.json
kindwise/resources/views.plant.json
kindwise/settings.py
kindwise/tests/__init__.py
kindwise/tests/conftest.py
kindwise/tests/resources/images/aloe-vera.jpg
kindwise/tests/resources/images/amanita_muscaria.jpg
kindwise/tests/resources/images/bee.jpeg
kindwise/tests/resources/images/padli.png
kindwise/tests/test_core.py
kindwise/tests/test_insect.py
kindwise/tests/test_mushroom.py
kindwise/tests/test_plant.py
kindwise-0.1.2.dist-info/WHEEL
kindwise-0.1.2.dist-info/METADATA
kindwise-0.1.2.dist-info/RECORD
