Metadata-Version: 2.1
Name: kindwise
Version: 0.1.2
Summary: Python SDK toolkit for integrating Kindwise API
Home-page: https://github.com/flowerchecker/kindwise
License: MIT
Author: Simon Plhak
Author-email: simon.plhak@flowerchecker.com
Requires-Python: >=3.10,<4.0
Classifier: License :: OSI Approved :: MIT License
Classifier: Programming Language :: Python :: 3
Classifier: Programming Language :: Python :: 3.10
Classifier: Programming Language :: Python :: 3.11
Requires-Dist: pillow
Requires-Dist: python-dotenv
Requires-Dist: requests
Project-URL: Repository, https://github.com/flowerchecker/kindwise
